odoo9_addon_mail_optional_follower_notification-9.0.1.0.0.99.dev13-py3.8-nspkg.pth
odoo_addons/mail_optional_follower_notification/README.rst
odoo_addons/mail_optional_follower_notification/__init__.py
odoo_addons/mail_optional_follower_notification/__openerp__.py
odoo_addons/mail_optional_follower_notification/i18n/am.po
odoo_addons/mail_optional_follower_notification/i18n/ar.po
odoo_addons/mail_optional_follower_notification/i18n/bg.po
odoo_addons/mail_optional_follower_notification/i18n/bs.po
odoo_addons/mail_optional_follower_notification/i18n/ca.po
odoo_addons/mail_optional_follower_notification/i18n/cs.po
odoo_addons/mail_optional_follower_notification/i18n/da.po
odoo_addons/mail_optional_follower_notification/i18n/de.po
odoo_addons/mail_optional_follower_notification/i18n/el_GR.po
odoo_addons/mail_optional_follower_notification/i18n/en.po
odoo_addons/mail_optional_follower_notification/i18n/en_GB.po
odoo_addons/mail_optional_follower_notification/i18n/es.po
odoo_addons/mail_optional_follower_notification/i18n/es_CO.po
odoo_addons/mail_optional_follower_notification/i18n/es_CR.po
odoo_addons/mail_optional_follower_notification/i18n/es_EC.po
odoo_addons/mail_optional_follower_notification/i18n/es_MX.po
odoo_addons/mail_optional_follower_notification/i18n/es_VE.po
odoo_addons/mail_optional_follower_notification/i18n/et.po
odoo_addons/mail_optional_follower_notification/i18n/eu.po
odoo_addons/mail_optional_follower_notification/i18n/fi.po
odoo_addons/mail_optional_follower_notification/i18n/fr.po
odoo_addons/mail_optional_follower_notification/i18n/fr_CA.po
odoo_addons/mail_optional_follower_notification/i18n/fr_CH.po
odoo_addons/mail_optional_follower_notification/i18n/gl.po
odoo_addons/mail_optional_follower_notification/i18n/hr.po
odoo_addons/mail_optional_follower_notification/i18n/hr_HR.po
odoo_addons/mail_optional_follower_notification/i18n/hu.po
odoo_addons/mail_optional_follower_notification/i18n/id.po
odoo9_addon_mail_optional_follower_notification-9.0.1.0.0.99.dev13.dist-info/METADATA
odoo9_addon_mail_optional_follower_notification-9.0.1.0.0.99.dev13.dist-info/WHEEL
odoo9_addon_mail_optional_follower_notification-9.0.1.0.0.99.dev13.dist-info/namespace_packages.txt
odoo9_addon_mail_optional_follower_notification-9.0.1.0.0.99.dev13.dist-info/top_level.txt
odoo9_addon_mail_optional_follower_notification-9.0.1.0.0.99.dev13.dist-info/RECORD
